sweepr/__init__.py
sweepr/run.py
sweepr/sweep.py
sweepr/types.py
sweepr/utils.py
sweepr/executors/__init__.py
sweepr/executors/base.py
sweepr/executors/pueue.py
sweepr/executors/python.py
sweepr/executors/slurm.py
sweepr/providers/__init__.py
sweepr/providers/base.py
sweepr/providers/wandb.py
sweepr-0.1.2.dist-info/LICENSE
sweepr-0.1.2.dist-info/METADATA
sweepr-0.1.2.dist-info/WHEEL
sweepr-0.1.2.dist-info/top_level.txt
sweepr-0.1.2.dist-info/RECORD
