Metadata-Version: 2.1
Name: sweepr
Version: 0.1.2
Summary: Pythonic interface to experiment configuration generation. Sweep clean!
License: Apache License 2.0
Requires-Python: >=3.10
License-File: LICENSE
Requires-Dist: fire
Requires-Dist: polars
Requires-Dist: tqdm
Provides-Extra: dev
Requires-Dist: ruff; extra == "dev"
Requires-Dist: sweepr[wandb]; extra == "dev"
Provides-Extra: wandb
Requires-Dist: wandb; extra == "wandb"
